edgegap_fixtures/__init__.py
edgegap_fixtures/_consul.py
edgegap_fixtures/_sqlite.py
edgegap_fixtures-1.0.0.dist-info/LICENSE
edgegap_fixtures-1.0.0.dist-info/METADATA
edgegap_fixtures-1.0.0.dist-info/WHEEL
edgegap_fixtures-1.0.0.dist-info/RECORD
