Metadata-Version: 2.1
Name: edgegap-fixtures
Version: 1.0.0
Summary: The Edgegap Fixtures library includes various tools and helpers for interacting with Pytest Fixtures
Author: Bastien Roy
Author-email: bastien@edgegap.com
Requires-Python: >=3.10,<4.0
Classifier: Programming Language :: Python :: 3
Classifier: Programming Language :: Python :: 3.10
Classifier: Programming Language :: Python :: 3.11
Classifier: Programming Language :: Python :: 3.12
Requires-Dist: edgegap-consul (>=1.7.0,<2.0.0)
Requires-Dist: pytest (>=8.2.0,<9.0.0)
Requires-Dist: sqlmodel (>=0.0.18,<0.0.19)
